phpdoc_trans/__init__.py
phpdoc_trans/main.py
phpdoc_trans/spinner.py
phpdoc_trans-0.0.5.dist-info/LICENSE
phpdoc_trans-0.0.5.dist-info/METADATA
phpdoc_trans-0.0.5.dist-info/WHEEL
phpdoc_trans-0.0.5.dist-info/entry_points.txt
phpdoc_trans-0.0.5.dist-info/top_level.txt
phpdoc_trans-0.0.5.dist-info/RECORD
