Metadata-Version: 2.1
Name: phpdoc-trans
Version: 0.0.5
Summary: PHP doc transaction tool
Home-page: https://github.com/AtlanticF/phpdoc-openai-trans
Author: meifeng.song
Author-email: atlanticfeng@icloud.com
Classifier: Programming Language :: Python :: 3
Classifier: License :: OSI Approved :: MIT License
Classifier: Operating System :: OS Independent
License-File: LICENSE
Requires-Dist: click
Requires-Dist: openai
Requires-Dist: bs4
Requires-Dist: progress
